{
	"part": "back",
	"model": "geo/equipment/jetpack.geo.json",
	"texture": "textures/entity/jetpack.png",

	"attachments": [
		{
			"mode": "add",
			"frame": "back_slot",
			"armor": "jetpack_base"
		},
		{
			"mode": "add",
			"frame": "left_jet_frame",
			"armor": "left_jet_base"
		},
		{
			"mode": "add",
			"frame": "right_jet_frame",
			"armor": "right_jet_base"
		},
		{
			"mode": "add",
			"frame": "left_jet2_frame",
			"armor": "left_jet"
		},
		{
			"mode": "add",
			"frame": "right_jet2_frame",
			"armor": "right_jet"
		}
	]
}